onncas
