Metadata-Version: 2.1
Name: onncas
Version: 0.0.3
Summary: Convenience module for interacting with Trend Micro Cloud App Security (CAS)
Home-page: http://oznetnerd.com
Author: Will Robinson
Author-email: will@oznetnerd.com
License: UNKNOWN
Platform: UNKNOWN
